{"client.features.hudOpacity":false,"common.features.fireAspect":false,"client.features.pickupAnimations":false,"common.features.fertilizableBlocks":false,"common.features.fernBonemeal":false,"client.features.reacharoundPlacement":false,"client.features.savingOverlay":false,"common.features.recipes":false,"client.features.screenSafeArea":false,"client.features.worldColorNoise":false,"client.core.clientRenderTimer":true,"client.features.slotHighlight":false,"client.features.biggerDraggingItem":false,"client.features.fishingBobber":true,"client.features.chat":false,"client.features.bedrockShading":false,"client.features.loadingScreens":false,"client.features.heldItemTooltips":false,"client.features.idleHandAnimations":false,"client.features.eatingAnimations":false,"common.features.animalEatingParticles":false,"client.core.bedrockIfyButton":false,"client.features.useAnimations":true,"client.features.panoramaBackground":false}